mutt_oauth2/__init__.py
mutt_oauth2/__main__.py
mutt_oauth2/constants.py
mutt_oauth2/main.py
mutt_oauth2/py.typed
mutt_oauth2/registrations.py
mutt_oauth2/utils.py
mutt_oauth2-0.1.2.dist-info/METADATA
mutt_oauth2-0.1.2.dist-info/WHEEL
mutt_oauth2-0.1.2.dist-info/entry_points.txt
mutt_oauth2-0.1.2.dist-info/licenses/LICENSE.txt
mutt_oauth2-0.1.2.dist-info/RECORD
