Metadata-Version: 2.4
Name: mutt-oauth2
Version: 0.1.2
Summary: Packaged, maintained version of contributed mutt_oauth2.py script.
License-Expression: MIT
License-File: LICENSE.txt
Keywords: email,gmail,mutt,outlook
Author: Andrew Udvare
Author-email: audvare@gmail.com
Requires-Python: >=3.10,<4.0
Classifier: Development Status :: 4 - Beta
Classifier: Intended Audience :: Developers
Classifier: Programming Language :: Python
Classifier: Programming Language :: Python :: 3.10
Classifier: Programming Language :: Python :: 3.11
Classifier: Programming Language :: Python :: 3.12
Classifier: Programming Language :: Python :: 3.13
Classifier: Programming Language :: Python :: 3.14
Classifier: Typing :: Typed
Requires-Dist: bascom (>=0.1.0,<0.2.0)
Requires-Dist: click (>=8.3.1,<9.0.0)
Requires-Dist: keyring (>=25.7.0,<26.0.0)
Requires-Dist: requests (>=2.32.5,<3.0.0)
Requires-Dist: typing-extensions (>=4.15.0,<5.0.0)
Project-URL: Documentation, https://mutt-oauth2.readthedocs.org
Project-URL: Homepage, https://tatsh.github.io/mutt-oauth2/
Project-URL: Issues, https://github.com/Tatsh/mutt-oauth2/issues
Project-URL: Repository, https://github.com/Tatsh/mutt-oauth2
